BiliHome/__init__.py
BiliHome/bili.py
bilihome-0.1.0.dist-info/METADATA
bilihome-0.1.0.dist-info/WHEEL
bilihome-0.1.0.dist-info/top_level.txt
bilihome-0.1.0.dist-info/RECORD
