Metadata-Version: 2.4
Name: BiliHome
Version: 0.1.0
Summary: 一个用于获取B站用户信息的Python包
Home-page: https://github.com/Moxin1044/BiliHome
Author: Moxin
Author-email: 1044631097@qq.com
License: MIT
Project-URL: Bug Reports, https://github.com/Moxin1044/BiliHome/issues
Project-URL: Source, https://github.com/Moxin1044/BiliHome
Keywords: bilibili,api,user-info
Classifier: Development Status :: 3 - Alpha
Classifier: Intended Audience :: Developers
Classifier: License :: OSI Approved :: MIT License
Classifier: Operating System :: OS Independent
Classifier: Programming Language :: Python :: 3
Classifier: Programming Language :: Python :: 3 :: Only
Classifier: Programming Language :: Python :: 3.6
Classifier: Programming Language :: Python :: 3.7
Classifier: Programming Language :: Python :: 3.8
Classifier: Programming Language :: Python :: 3.9
Classifier: Programming Language :: Python :: 3.10
Classifier: Programming Language :: Python :: 3.11
Requires-Python: >=3.6
Requires-Dist: requests>=2.25.0
Dynamic: author
Dynamic: author-email
Dynamic: classifier
Dynamic: description
Dynamic: description-content-type
Dynamic: home-page
Dynamic: keywords
Dynamic: license
Dynamic: project-url
Dynamic: requires-dist
Dynamic: requires-python
Dynamic: summary
